aityz/__init__.py
aityz/encryption.py
aityz/exceptions.py
aityz/nlp.py
aityz-1.1.0.dist-info/LICENSE
aityz-1.1.0.dist-info/METADATA
aityz-1.1.0.dist-info/WHEEL
aityz-1.1.0.dist-info/top_level.txt
aityz-1.1.0.dist-info/RECORD
