Metadata-Version: 2.1
Name: aityz
Version: 1.1.0
Summary: The multipurpose package, built for programmers
Home-page: https://github.com/Aityz/Library
Author: Aityz
Author-email: itzaityz@gmail.com
License: UNKNOWN
Platform: UNKNOWN
License-File: LICENSE
Requires-Dist: rsa
Requires-Dist: torch
Requires-Dist: pycryptodome
Requires-Dist: transformers
Requires-Dist: accelerate
